kore_shell/__init__.py
kore_shell/shells.py
kore_shell/lib/__init__.py
kore_shell/lib/dict.py
kore_shell/lib/parsers.py
kore_shell-0.0.2.data/scripts/kore-shell
kore_shell-0.0.2.dist-info/DESCRIPTION.rst
kore_shell-0.0.2.dist-info/METADATA
kore_shell-0.0.2.dist-info/metadata.json
kore_shell-0.0.2.dist-info/RECORD
kore_shell-0.0.2.dist-info/top_level.txt
kore_shell-0.0.2.dist-info/WHEEL
